mates/__init__.py
mates/commands.py
mates/constants.py
mates/controller.py
mates/data.py
mates_controller-1.0.9.dist-info/LICENSE
mates_controller-1.0.9.dist-info/METADATA
mates_controller-1.0.9.dist-info/WHEEL
mates_controller-1.0.9.dist-info/top_level.txt
mates_controller-1.0.9.dist-info/RECORD
