Metadata-Version: 2.1
Name: mates-controller
Version: 1.0.9
Summary: A Python Library developed to be used with Mates Studio Commander and Architect Environments
Home-page: https://github.com/BreadBoardMates/Python-Mates-Controller
Author: Breadboard Mates
Author-email: developers@breadboardmates.com
Project-URL: Bug Tracker, https://github.com/BreadBoardMates/Python-Mates-Controller/issues
Classifier: Programming Language :: Python :: 3
Classifier: License :: OSI Approved :: MIT License
Classifier: Operating System :: OS Independent
Requires-Python: >=3.6
License-File: LICENSE
Requires-Dist: pyserial (>=3.5)
Requires-Dist: Pillow (>=9.0.1)
